progmon/__init__.py
progmon-0.1.0.dist-info/METADATA
progmon-0.1.0.dist-info/WHEEL
progmon-0.1.0.dist-info/licenses/LICENSE.txt
progmon-0.1.0.dist-info/RECORD
