Metadata-Version: 2.1
Name: progmon
Version: 0.1.0
Summary: This module offers different methods to show the current status of an iterative calculation algorithm or to control its execution, i.e. abort it when certain criterions are met.
Project-URL: Source, https://github.com/proggy/progmon
Project-URL: Homepage, https://github.com/proggy/progmon
Project-URL: Bug Tracker, https://github.com/proggy/progmon/issues
Author-email: Daniel Jung <proggy-contact@mailbox.org>
Maintainer-email: Daniel Jung <proggy-contact@mailbox.org>
License-File: LICENSE.txt
Classifier: License :: OSI Approved :: GNU General Public License v2 (GPLv2)
Classifier: Operating System :: OS Independent
Classifier: Programming Language :: Python :: 3
Requires-Python: >=3.7
